[
  {
      "scouter": "SOS",
      "matchNumber": 1,
      "robot": 5,
      "teamNumber": 8836,
      "startPosition": 2,
      "isNoShow": false,
      "hasMoved": false,
      "autoSpeakerScoredCount": 3,
      "autoSpeakerMissedCount": 0,
      "autoGamePiecePath": 157,
      "autoFoulCount": 0,
      "ampScoredCount": 0,
      "speakerScoredCount": 7,
      "feederShotsCount": 0,
      "noteInTrapCount": 0,
      "teleopFoulCount": 0,
      "endPosition": 1,
      "offenseSkillRating": 3,
      "defenseSkillRating": 1,
      "hasDiedOrTippedOver": false,
      "yellowRedCard": 1,
      "comments": "Hi There! SOS - match (1)"
  },
  {
      "scouter": "SOS",
      "matchNumber": 2,
      "robot": 5,
      "teamNumber": 2503,
      "startPosition": 2,
      "isNoShow": false,
      "hasMoved": false,
      "autoSpeakerScoredCount": 0,
      "autoSpeakerMissedCount": 0,
      "autoGamePiecePath": 27,
      "autoFoulCount": 0,
      "ampScoredCount": 0,
      "speakerScoredCount": 0,
      "feederShotsCount": 0,
      "noteInTrapCount": 0,
      "teleopFoulCount": 1,
      "endPosition": 3,
      "offenseSkillRating": 2,
      "defenseSkillRating": 3,
      "hasDiedOrTippedOver": false,
      "yellowRedCard": 1,
      "comments": "Hi There! SOS - match (2)"
  },
  {
      "scouter": "SOS",
      "matchNumber": 3,
      "robot": 5,
      "teamNumber": 8516,
      "startPosition": 2,
      "isNoShow": false,
      "hasMoved": false,
      "autoSpeakerScoredCount": 1,
      "autoSpeakerMissedCount": 0,
      "autoGamePiecePath": 247,
      "autoFoulCount": 0,
      "ampScoredCount": 2,
      "speakerScoredCount": 11,
      "feederShotsCount": 0,
      "noteInTrapCount": 0,
      "teleopFoulCount": 0,
      "endPosition": 1,
      "offenseSkillRating": 1,
      "defenseSkillRating": 1,
      "hasDiedOrTippedOver": false,
      "yellowRedCard": 1,
      "comments": "Hi There! SOS - match (3)"
  },
  {
      "scouter": "SOS",
      "matchNumber": 4,
      "robot": 5,
      "teamNumber": 4778,
      "startPosition": 2,
      "isNoShow": false,
      "hasMoved": true,
      "autoSpeakerScoredCount": 3,
      "autoSpeakerMissedCount": 0,
      "autoGamePiecePath": 63,
      "autoFoulCount": 0,
      "ampScoredCount": 2,
      "speakerScoredCount": 4,
      "feederShotsCount": 0,
      "noteInTrapCount": 0,
      "teleopFoulCount": 0,
      "endPosition": 1,
      "offenseSkillRating": 1,
      "defenseSkillRating": 2,
      "hasDiedOrTippedOver": false,
      "yellowRedCard": 1,
      "comments": "Hi There! SOS - match (4)"
  },
  {
      "scouter": "SOS",
      "matchNumber": 5,
      "robot": 5,
      "teamNumber": 2239,
      "startPosition": 2,
      "isNoShow": false,
      "hasMoved": true,
      "autoSpeakerScoredCount": 1,
      "autoSpeakerMissedCount": 0,
      "autoGamePiecePath": 195,
      "autoFoulCount": 0,
      "ampScoredCount": 5,
      "speakerScoredCount": 9,
      "feederShotsCount": 0,
      "noteInTrapCount": 0,
      "teleopFoulCount": 0,
      "endPosition": 1,
      "offenseSkillRating": 2,
      "defenseSkillRating": 1,
      "hasDiedOrTippedOver": false,
      "yellowRedCard": 1,
      "comments": "Hi There! SOS - match (5)"
  },
  {
      "scouter": "SOS",
      "matchNumber": 6,
      "robot": 5,
      "teamNumber": 6318,
      "startPosition": 2,
      "isNoShow": false,
      "hasMoved": true,
      "autoSpeakerScoredCount": 0,
      "autoSpeakerMissedCount": 0,
      "autoGamePiecePath": 9,
      "autoFoulCount": 1,
      "ampScoredCount": 0,
      "speakerScoredCount": 0,
      "feederShotsCount": 0,
      "noteInTrapCount": 0,
      "teleopFoulCount": 1,
      "endPosition": 4,
      "offenseSkillRating": 1,
      "defenseSkillRating": 2,
      "hasDiedOrTippedOver": false,
      "yellowRedCard": 1,
      "comments": "Hi There! SOS - match (6)"
  },
  {
      "scouter": "SOS",
      "matchNumber": 7,
      "robot": 5,
      "teamNumber": 4511,
      "startPosition": 2,
      "isNoShow": false,
      "hasMoved": true,
      "autoSpeakerScoredCount": 0,
      "autoSpeakerMissedCount": 0,
      "autoGamePiecePath": 150,
      "autoFoulCount": 0,
      "ampScoredCount": 4,
      "speakerScoredCount": 9,
      "feederShotsCount": 0,
      "noteInTrapCount": 0,
      "teleopFoulCount": 0,
      "endPosition": 0,
      "offenseSkillRating": 2,
      "defenseSkillRating": 0,
      "hasDiedOrTippedOver": false,
      "yellowRedCard": 1,
      "comments": "Hi There! SOS - match (7)"
  },
  {
      "scouter": "SOS",
      "matchNumber": 8,
      "robot": 5,
      "teamNumber": 4741,
      "startPosition": 2,
      "isNoShow": false,
      "hasMoved": true,
      "autoSpeakerScoredCount": 1,
      "autoSpeakerMissedCount": 0,
      "autoGamePiecePath": 141,
      "autoFoulCount": 2,
      "ampScoredCount": 5,
      "speakerScoredCount": 9,
      "feederShotsCount": 0,
      "noteInTrapCount": 0,
      "teleopFoulCount": 0,
      "endPosition": 4,
      "offenseSkillRating": 3,
      "defenseSkillRating": 1,
      "hasDiedOrTippedOver": false,
      "yellowRedCard": 1,
      "comments": "Hi There! SOS - match (8)"
  },
  {
      "scouter": "SOS",
      "matchNumber": 9,
      "robot": 5,
      "teamNumber": 5278,
      "startPosition": 2,
      "isNoShow": false,
      "hasMoved": true,
      "autoSpeakerScoredCount": 1,
      "autoSpeakerMissedCount": 0,
      "autoGamePiecePath": 186,
      "autoFoulCount": 2,
      "ampScoredCount": 3,
      "speakerScoredCount": 6,
      "feederShotsCount": 0,
      "noteInTrapCount": 0,
      "teleopFoulCount": 0,
      "endPosition": 3,
      "offenseSkillRating": 2,
      "defenseSkillRating": 0,
      "hasDiedOrTippedOver": false,
      "yellowRedCard": 1,
      "comments": "Hi There! SOS - match (9)"
  },
  {
      "scouter": "SOS",
      "matchNumber": 10,
      "robot": 5,
      "teamNumber": 5143,
      "startPosition": 2,
      "isNoShow": false,
      "hasMoved": true,
      "autoSpeakerScoredCount": 1,
      "autoSpeakerMissedCount": 0,
      "autoGamePiecePath": 233,
      "autoFoulCount": 3,
      "ampScoredCount": 3,
      "speakerScoredCount": 1,
      "feederShotsCount": 0,
      "noteInTrapCount": 0,
      "teleopFoulCount": 0,
      "endPosition": 4,
      "offenseSkillRating": 0,
      "defenseSkillRating": 0,
      "hasDiedOrTippedOver": false,
      "yellowRedCard": 1,
      "comments": "Hi There! SOS - match (10)"
  },
  {
      "scouter": "SOS",
      "matchNumber": 11,
      "robot": 5,
      "teamNumber": 4009,
      "startPosition": 2,
      "isNoShow": false,
      "hasMoved": true,
      "autoSpeakerScoredCount": 5,
      "autoSpeakerMissedCount": 0,
      "autoGamePiecePath": 185,
      "autoFoulCount": 0,
      "ampScoredCount": 5,
      "speakerScoredCount": 11,
      "feederShotsCount": 0,
      "noteInTrapCount": 0,
      "teleopFoulCount": 0,
      "endPosition": 4,
      "offenseSkillRating": 0,
      "defenseSkillRating": 2,
      "hasDiedOrTippedOver": false,
      "yellowRedCard": 1,
      "comments": "Hi There! SOS - match (11)"
  },
  {
      "scouter": "SOS",
      "matchNumber": 12,
      "robot": 5,
      "teamNumber": 9532,
      "startPosition": 2,
      "isNoShow": false,
      "hasMoved": false,
      "autoSpeakerScoredCount": 1,
      "autoSpeakerMissedCount": 0,
      "autoGamePiecePath": 10,
      "autoFoulCount": 0,
      "ampScoredCount": 4,
      "speakerScoredCount": 3,
      "feederShotsCount": 0,
      "noteInTrapCount": 0,
      "teleopFoulCount": 1,
      "endPosition": 0,
      "offenseSkillRating": 0,
      "defenseSkillRating": 1,
      "hasDiedOrTippedOver": false,
      "yellowRedCard": 1,
      "comments": "Hi There! SOS - match (12)"
  },
  {
      "scouter": "SOS",
      "matchNumber": 13,
      "robot": 5,
      "teamNumber": 2531,
      "startPosition": 2,
      "isNoShow": false,
      "hasMoved": false,
      "autoSpeakerScoredCount": 3,
      "autoSpeakerMissedCount": 0,
      "autoGamePiecePath": 85,
      "autoFoulCount": 0,
      "ampScoredCount": 6,
      "speakerScoredCount": 10,
      "feederShotsCount": 0,
      "noteInTrapCount": 0,
      "teleopFoulCount": 0,
      "endPosition": 4,
      "offenseSkillRating": 2,
      "defenseSkillRating": 0,
      "hasDiedOrTippedOver": true,
      "yellowRedCard": 1,
      "comments": "Hi There! SOS - match (13)"
  },
  {
      "scouter": "SOS",
      "matchNumber": 14,
      "robot": 5,
      "teamNumber": 4174,
      "startPosition": 2,
      "isNoShow": false,
      "hasMoved": true,
      "autoSpeakerScoredCount": 1,
      "autoSpeakerMissedCount": 0,
      "autoGamePiecePath": 88,
      "autoFoulCount": 1,
      "ampScoredCount": 2,
      "speakerScoredCount": 8,
      "feederShotsCount": 0,
      "noteInTrapCount": 0,
      "teleopFoulCount": 0,
      "endPosition": 3,
      "offenseSkillRating": 3,
      "defenseSkillRating": 3,
      "hasDiedOrTippedOver": true,
      "yellowRedCard": 1,
      "comments": "Hi There! SOS - match (14)"
  },
  {
      "scouter": "SOS",
      "matchNumber": 15,
      "robot": 5,
      "teamNumber": 93,
      "startPosition": 2,
      "isNoShow": false,
      "hasMoved": true,
      "autoSpeakerScoredCount": 1,
      "autoSpeakerMissedCount": 0,
      "autoGamePiecePath": 246,
      "autoFoulCount": 0,
      "ampScoredCount": 0,
      "speakerScoredCount": 11,
      "feederShotsCount": 0,
      "noteInTrapCount": 0,
      "teleopFoulCount": 1,
      "endPosition": 3,
      "offenseSkillRating": 1,
      "defenseSkillRating": 3,
      "hasDiedOrTippedOver": false,
      "yellowRedCard": 1,
      "comments": "Hi There! SOS - match (15)"
  },
  {
      "scouter": "SOS",
      "matchNumber": 16,
      "robot": 5,
      "teamNumber": 7038,
      "startPosition": 2,
      "isNoShow": false,
      "hasMoved": false,
      "autoSpeakerScoredCount": 3,
      "autoSpeakerMissedCount": 0,
      "autoGamePiecePath": 208,
      "autoFoulCount": 0,
      "ampScoredCount": 0,
      "speakerScoredCount": 12,
      "feederShotsCount": 0,
      "noteInTrapCount": 0,
      "teleopFoulCount": 1,
      "endPosition": 4,
      "offenseSkillRating": 0,
      "defenseSkillRating": 3,
      "hasDiedOrTippedOver": false,
      "yellowRedCard": 1,
      "comments": "Hi There! SOS - match (16)"
  },
  {
      "scouter": "SOS",
      "matchNumber": 17,
      "robot": 5,
      "teamNumber": 6709,
      "startPosition": 2,
      "isNoShow": false,
      "hasMoved": true,
      "autoSpeakerScoredCount": 2,
      "autoSpeakerMissedCount": 0,
      "autoGamePiecePath": 177,
      "autoFoulCount": 0,
      "ampScoredCount": 3,
      "speakerScoredCount": 5,
      "feederShotsCount": 0,
      "noteInTrapCount": 1,
      "teleopFoulCount": 0,
      "endPosition": 1,
      "offenseSkillRating": 0,
      "defenseSkillRating": 1,
      "hasDiedOrTippedOver": false,
      "yellowRedCard": 1,
      "comments": "Hi There! SOS - match (17)"
  },
  {
      "scouter": "SOS",
      "matchNumber": 18,
      "robot": 5,
      "teamNumber": 5826,
      "startPosition": 2,
      "isNoShow": false,
      "hasMoved": true,
      "autoSpeakerScoredCount": 1,
      "autoSpeakerMissedCount": 0,
      "autoGamePiecePath": 46,
      "autoFoulCount": 1,
      "ampScoredCount": 0,
      "speakerScoredCount": 8,
      "feederShotsCount": 0,
      "noteInTrapCount": 0,
      "teleopFoulCount": 0,
      "endPosition": 1,
      "offenseSkillRating": 2,
      "defenseSkillRating": 0,
      "hasDiedOrTippedOver": false,
      "yellowRedCard": 1,
      "comments": "Hi There! SOS - match (18)"
  },
  {
      "scouter": "SOS",
      "matchNumber": 19,
      "robot": 5,
      "teamNumber": 4693,
      "startPosition": 2,
      "isNoShow": false,
      "hasMoved": false,
      "autoSpeakerScoredCount": 3,
      "autoSpeakerMissedCount": 0,
      "autoGamePiecePath": 150,
      "autoFoulCount": 1,
      "ampScoredCount": 3,
      "speakerScoredCount": 6,
      "feederShotsCount": 0,
      "noteInTrapCount": 0,
      "teleopFoulCount": 0,
      "endPosition": 2,
      "offenseSkillRating": 2,
      "defenseSkillRating": 2,
      "hasDiedOrTippedOver": false,
      "yellowRedCard": 1,
      "comments": "Hi There! SOS - match (19)"
  },
  {
      "scouter": "SOS",
      "matchNumber": 20,
      "robot": 5,
      "teamNumber": 8298,
      "startPosition": 2,
      "isNoShow": false,
      "hasMoved": false,
      "autoSpeakerScoredCount": 2,
      "autoSpeakerMissedCount": 0,
      "autoGamePiecePath": 39,
      "autoFoulCount": 0,
      "ampScoredCount": 1,
      "speakerScoredCount": 7,
      "feederShotsCount": 0,
      "noteInTrapCount": 0,
      "teleopFoulCount": 1,
      "endPosition": 0,
      "offenseSkillRating": 1,
      "defenseSkillRating": 2,
      "hasDiedOrTippedOver": false,
      "yellowRedCard": 1,
      "comments": "Hi There! SOS - match (20)"
  },
  {
      "scouter": "SOS",
      "matchNumber": 21,
      "robot": 5,
      "teamNumber": 6160,
      "startPosition": 2,
      "isNoShow": false,
      "hasMoved": false,
      "autoSpeakerScoredCount": 3,
      "autoSpeakerMissedCount": 0,
      "autoGamePiecePath": 56,
      "autoFoulCount": 0,
      "ampScoredCount": 2,
      "speakerScoredCount": 6,
      "feederShotsCount": 0,
      "noteInTrapCount": 0,
      "teleopFoulCount": 0,
      "endPosition": 1,
      "offenseSkillRating": 3,
      "defenseSkillRating": 1,
      "hasDiedOrTippedOver": false,
      "yellowRedCard": 1,
      "comments": "Hi There! SOS - match (21)"
  },
  {
      "scouter": "SOS",
      "matchNumber": 22,
      "robot": 5,
      "teamNumber": 93,
      "startPosition": 2,
      "isNoShow": false,
      "hasMoved": true,
      "autoSpeakerScoredCount": 2,
      "autoSpeakerMissedCount": 0,
      "autoGamePiecePath": 81,
      "autoFoulCount": 0,
      "ampScoredCount": 0,
      "speakerScoredCount": 19,
      "feederShotsCount": 0,
      "noteInTrapCount": 0,
      "teleopFoulCount": 3,
      "endPosition": 4,
      "offenseSkillRating": 3,
      "defenseSkillRating": 1,
      "hasDiedOrTippedOver": false,
      "yellowRedCard": 1,
      "comments": "Hi There! SOS - match (22)"
  },
  {
      "scouter": "SOS",
      "matchNumber": 23,
      "robot": 5,
      "teamNumber": 5826,
      "startPosition": 2,
      "isNoShow": false,
      "hasMoved": false,
      "autoSpeakerScoredCount": 0,
      "autoSpeakerMissedCount": 0,
      "autoGamePiecePath": 217,
      "autoFoulCount": 0,
      "ampScoredCount": 0,
      "speakerScoredCount": 0,
      "feederShotsCount": 0,
      "noteInTrapCount": 0,
      "teleopFoulCount": 0,
      "endPosition": 4,
      "offenseSkillRating": 3,
      "defenseSkillRating": 3,
      "hasDiedOrTippedOver": false,
      "yellowRedCard": 1,
      "comments": "Hi There! SOS - match (23)"
  },
  {
      "scouter": "SOS",
      "matchNumber": 24,
      "robot": 5,
      "teamNumber": 2052,
      "startPosition": 2,
      "isNoShow": false,
      "hasMoved": true,
      "autoSpeakerScoredCount": 3,
      "autoSpeakerMissedCount": 0,
      "autoGamePiecePath": 111,
      "autoFoulCount": 0,
      "ampScoredCount": 1,
      "speakerScoredCount": 16,
      "feederShotsCount": 0,
      "noteInTrapCount": 0,
      "teleopFoulCount": 1,
      "endPosition": 2,
      "offenseSkillRating": 1,
      "defenseSkillRating": 3,
      "hasDiedOrTippedOver": false,
      "yellowRedCard": 1,
      "comments": "Hi There! SOS - match (24)"
  },
  {
      "scouter": "SOS",
      "matchNumber": 25,
      "robot": 5,
      "teamNumber": 1732,
      "startPosition": 2,
      "isNoShow": false,
      "hasMoved": true,
      "autoSpeakerScoredCount": 5,
      "autoSpeakerMissedCount": 0,
      "autoGamePiecePath": 2,
      "autoFoulCount": 0,
      "ampScoredCount": 5,
      "speakerScoredCount": 8,
      "feederShotsCount": 0,
      "noteInTrapCount": 0,
      "teleopFoulCount": 0,
      "endPosition": 0,
      "offenseSkillRating": 2,
      "defenseSkillRating": 2,
      "hasDiedOrTippedOver": false,
      "yellowRedCard": 1,
      "comments": "Hi There! SOS - match (25)"
  },
  {
      "scouter": "SOS",
      "matchNumber": 26,
      "robot": 5,
      "teamNumber": 7068,
      "startPosition": 2,
      "isNoShow": false,
      "hasMoved": false,
      "autoSpeakerScoredCount": 2,
      "autoSpeakerMissedCount": 0,
      "autoGamePiecePath": 239,
      "autoFoulCount": 4,
      "ampScoredCount": 3,
      "speakerScoredCount": 7,
      "feederShotsCount": 0,
      "noteInTrapCount": 0,
      "teleopFoulCount": 0,
      "endPosition": 2,
      "offenseSkillRating": 3,
      "defenseSkillRating": 0,
      "hasDiedOrTippedOver": false,
      "yellowRedCard": 1,
      "comments": "Hi There! SOS - match (26)"
  },
  {
      "scouter": "SOS",
      "matchNumber": 27,
      "robot": 5,
      "teamNumber": 7864,
      "startPosition": 2,
      "isNoShow": false,
      "hasMoved": true,
      "autoSpeakerScoredCount": 2,
      "autoSpeakerMissedCount": 0,
      "autoGamePiecePath": 212,
      "autoFoulCount": 0,
      "ampScoredCount": 3,
      "speakerScoredCount": 3,
      "feederShotsCount": 0,
      "noteInTrapCount": 0,
      "teleopFoulCount": 0,
      "endPosition": 1,
      "offenseSkillRating": 2,
      "defenseSkillRating": 1,
      "hasDiedOrTippedOver": false,
      "yellowRedCard": 1,
      "comments": "Hi There! SOS - match (27)"
  },
  {
      "scouter": "SOS",
      "matchNumber": 28,
      "robot": 5,
      "teamNumber": 7797,
      "startPosition": 2,
      "isNoShow": false,
      "hasMoved": false,
      "autoSpeakerScoredCount": 2,
      "autoSpeakerMissedCount": 0,
      "autoGamePiecePath": 57,
      "autoFoulCount": 1,
      "ampScoredCount": 3,
      "speakerScoredCount": 13,
      "feederShotsCount": 0,
      "noteInTrapCount": 0,
      "teleopFoulCount": 0,
      "endPosition": 4,
      "offenseSkillRating": 3,
      "defenseSkillRating": 3,
      "hasDiedOrTippedOver": false,
      "yellowRedCard": 1,
      "comments": "Hi There! SOS - match (28)"
  },
  {
      "scouter": "SOS",
      "matchNumber": 29,
      "robot": 5,
      "teamNumber": 8836,
      "startPosition": 2,
      "isNoShow": false,
      "hasMoved": false,
      "autoSpeakerScoredCount": 0,
      "autoSpeakerMissedCount": 0,
      "autoGamePiecePath": 83,
      "autoFoulCount": 0,
      "ampScoredCount": 6,
      "speakerScoredCount": 0,
      "feederShotsCount": 0,
      "noteInTrapCount": 0,
      "teleopFoulCount": 0,
      "endPosition": 3,
      "offenseSkillRating": 1,
      "defenseSkillRating": 3,
      "hasDiedOrTippedOver": false,
      "yellowRedCard": 1,
      "comments": "Hi There! SOS - match (29)"
  },
  {
      "scouter": "SOS",
      "matchNumber": 30,
      "robot": 5,
      "teamNumber": 8516,
      "startPosition": 2,
      "isNoShow": false,
      "hasMoved": false,
      "autoSpeakerScoredCount": 1,
      "autoSpeakerMissedCount": 0,
      "autoGamePiecePath": 217,
      "autoFoulCount": 0,
      "ampScoredCount": 5,
      "speakerScoredCount": 2,
      "feederShotsCount": 0,
      "noteInTrapCount": 0,
      "teleopFoulCount": 0,
      "endPosition": 1,
      "offenseSkillRating": 1,
      "defenseSkillRating": 0,
      "hasDiedOrTippedOver": false,
      "yellowRedCard": 1,
      "comments": "Hi There! SOS - match (30)"
  },
  {
      "scouter": "SOS",
      "matchNumber": 31,
      "robot": 5,
      "teamNumber": 1816,
      "startPosition": 2,
      "isNoShow": false,
      "hasMoved": true,
      "autoSpeakerScoredCount": 4,
      "autoSpeakerMissedCount": 0,
      "autoGamePiecePath": 197,
      "autoFoulCount": 0,
      "ampScoredCount": 3,
      "speakerScoredCount": 8,
      "feederShotsCount": 0,
      "noteInTrapCount": 0,
      "teleopFoulCount": 0,
      "endPosition": 0,
      "offenseSkillRating": 3,
      "defenseSkillRating": 3,
      "hasDiedOrTippedOver": false,
      "yellowRedCard": 1,
      "comments": "Hi There! SOS - match (31)"
  },
  {
      "scouter": "SOS",
      "matchNumber": 32,
      "robot": 5,
      "teamNumber": 6709,
      "startPosition": 2,
      "isNoShow": false,
      "hasMoved": true,
      "autoSpeakerScoredCount": 6,
      "autoSpeakerMissedCount": 0,
      "autoGamePiecePath": 74,
      "autoFoulCount": 0,
      "ampScoredCount": 7,
      "speakerScoredCount": 6,
      "feederShotsCount": 0,
      "noteInTrapCount": 0,
      "teleopFoulCount": 1,
      "endPosition": 4,
      "offenseSkillRating": 1,
      "defenseSkillRating": 0,
      "hasDiedOrTippedOver": true,
      "yellowRedCard": 1,
      "comments": "Hi There! SOS - match (32)"
  },
  {
      "scouter": "SOS",
      "matchNumber": 33,
      "robot": 5,
      "teamNumber": 2861,
      "startPosition": 2,
      "isNoShow": false,
      "hasMoved": true,
      "autoSpeakerScoredCount": 4,
      "autoSpeakerMissedCount": 0,
      "autoGamePiecePath": 133,
      "autoFoulCount": 0,
      "ampScoredCount": 4,
      "speakerScoredCount": 9,
      "feederShotsCount": 0,
      "noteInTrapCount": 0,
      "teleopFoulCount": 1,
      "endPosition": 3,
      "offenseSkillRating": 2,
      "defenseSkillRating": 0,
      "hasDiedOrTippedOver": false,
      "yellowRedCard": 1,
      "comments": "Hi There! SOS - match (33)"
  },
  {
      "scouter": "SOS",
      "matchNumber": 34,
      "robot": 5,
      "teamNumber": 2847,
      "startPosition": 2,
      "isNoShow": false,
      "hasMoved": true,
      "autoSpeakerScoredCount": 3,
      "autoSpeakerMissedCount": 0,
      "autoGamePiecePath": 199,
      "autoFoulCount": 0,
      "ampScoredCount": 2,
      "speakerScoredCount": 8,
      "feederShotsCount": 0,
      "noteInTrapCount": 0,
      "teleopFoulCount": 0,
      "endPosition": 2,
      "offenseSkillRating": 3,
      "defenseSkillRating": 3,
      "hasDiedOrTippedOver": false,
      "yellowRedCard": 1,
      "comments": "Hi There! SOS - match (34)"
  },
  {
      "scouter": "SOS",
      "matchNumber": 35,
      "robot": 5,
      "teamNumber": 7915,
      "startPosition": 2,
      "isNoShow": false,
      "hasMoved": true,
      "autoSpeakerScoredCount": 1,
      "autoSpeakerMissedCount": 0,
      "autoGamePiecePath": 70,
      "autoFoulCount": 1,
      "ampScoredCount": 2,
      "speakerScoredCount": 6,
      "feederShotsCount": 0,
      "noteInTrapCount": 0,
      "teleopFoulCount": 1,
      "endPosition": 0,
      "offenseSkillRating": 0,
      "defenseSkillRating": 2,
      "hasDiedOrTippedOver": false,
      "yellowRedCard": 1,
      "comments": "Hi There! SOS - match (35)"
  },
  {
      "scouter": "SOS",
      "matchNumber": 36,
      "robot": 5,
      "teamNumber": 4624,
      "startPosition": 2,
      "isNoShow": false,
      "hasMoved": false,
      "autoSpeakerScoredCount": 3,
      "autoSpeakerMissedCount": 0,
      "autoGamePiecePath": 145,
      "autoFoulCount": 0,
      "ampScoredCount": 0,
      "speakerScoredCount": 15,
      "feederShotsCount": 0,
      "noteInTrapCount": 0,
      "teleopFoulCount": 0,
      "endPosition": 3,
      "offenseSkillRating": 1,
      "defenseSkillRating": 1,
      "hasDiedOrTippedOver": false,
      "yellowRedCard": 1,
      "comments": "Hi There! SOS - match (36)"
  },
  {
      "scouter": "SOS",
      "matchNumber": 37,
      "robot": 5,
      "teamNumber": 3197,
      "startPosition": 2,
      "isNoShow": false,
      "hasMoved": true,
      "autoSpeakerScoredCount": 2,
      "autoSpeakerMissedCount": 0,
      "autoGamePiecePath": 110,
      "autoFoulCount": 0,
      "ampScoredCount": 1,
      "speakerScoredCount": 11,
      "feederShotsCount": 0,
      "noteInTrapCount": 0,
      "teleopFoulCount": 1,
      "endPosition": 0,
      "offenseSkillRating": 1,
      "defenseSkillRating": 3,
      "hasDiedOrTippedOver": false,
      "yellowRedCard": 1,
      "comments": "Hi There! SOS - match (37)"
  },
  {
      "scouter": "SOS",
      "matchNumber": 38,
      "robot": 5,
      "teamNumber": 2531,
      "startPosition": 2,
      "isNoShow": false,
      "hasMoved": true,
      "autoSpeakerScoredCount": 1,
      "autoSpeakerMissedCount": 0,
      "autoGamePiecePath": 79,
      "autoFoulCount": 2,
      "ampScoredCount": 3,
      "speakerScoredCount": 5,
      "feederShotsCount": 0,
      "noteInTrapCount": 0,
      "teleopFoulCount": 0,
      "endPosition": 3,
      "offenseSkillRating": 0,
      "defenseSkillRating": 3,
      "hasDiedOrTippedOver": false,
      "yellowRedCard": 1,
      "comments": "Hi There! SOS - match (38)"
  },
  {
      "scouter": "SOS",
      "matchNumber": 39,
      "robot": 5,
      "teamNumber": 8836,
      "startPosition": 2,
      "isNoShow": false,
      "hasMoved": true,
      "autoSpeakerScoredCount": 4,
      "autoSpeakerMissedCount": 0,
      "autoGamePiecePath": 255,
      "autoFoulCount": 0,
      "ampScoredCount": 3,
      "speakerScoredCount": 6,
      "feederShotsCount": 0,
      "noteInTrapCount": 0,
      "teleopFoulCount": 0,
      "endPosition": 4,
      "offenseSkillRating": 1,
      "defenseSkillRating": 3,
      "hasDiedOrTippedOver": false,
      "yellowRedCard": 1,
      "comments": "Hi There! SOS - match (39)"
  },
  {
      "scouter": "SOS",
      "matchNumber": 40,
      "robot": 5,
      "teamNumber": 2977,
      "startPosition": 2,
      "isNoShow": false,
      "hasMoved": true,
      "autoSpeakerScoredCount": 3,
      "autoSpeakerMissedCount": 0,
      "autoGamePiecePath": 77,
      "autoFoulCount": 0,
      "ampScoredCount": 2,
      "speakerScoredCount": 13,
      "feederShotsCount": 0,
      "noteInTrapCount": 0,
      "teleopFoulCount": 0,
      "endPosition": 0,
      "offenseSkillRating": 3,
      "defenseSkillRating": 0,
      "hasDiedOrTippedOver": false,
      "yellowRedCard": 1,
      "comments": "Hi There! SOS - match (40)"
  },
  {
      "scouter": "SOS",
      "matchNumber": 41,
      "robot": 5,
      "teamNumber": 5253,
      "startPosition": 2,
      "isNoShow": false,
      "hasMoved": true,
      "autoSpeakerScoredCount": 1,
      "autoSpeakerMissedCount": 0,
      "autoGamePiecePath": 78,
      "autoFoulCount": 0,
      "ampScoredCount": 2,
      "speakerScoredCount": 10,
      "feederShotsCount": 0,
      "noteInTrapCount": 0,
      "teleopFoulCount": 0,
      "endPosition": 3,
      "offenseSkillRating": 0,
      "defenseSkillRating": 0,
      "hasDiedOrTippedOver": false,
      "yellowRedCard": 1,
      "comments": "Hi There! SOS - match (41)"
  },
  {
      "scouter": "SOS",
      "matchNumber": 42,
      "robot": 5,
      "teamNumber": 930,
      "startPosition": 2,
      "isNoShow": false,
      "hasMoved": true,
      "autoSpeakerScoredCount": 2,
      "autoSpeakerMissedCount": 0,
      "autoGamePiecePath": 173,
      "autoFoulCount": 0,
      "ampScoredCount": 6,
      "speakerScoredCount": 10,
      "feederShotsCount": 0,
      "noteInTrapCount": 0,
      "teleopFoulCount": 1,
      "endPosition": 1,
      "offenseSkillRating": 1,
      "defenseSkillRating": 2,
      "hasDiedOrTippedOver": false,
      "yellowRedCard": 1,
      "comments": "Hi There! SOS - match (42)"
  },
  {
      "scouter": "SOS",
      "matchNumber": 43,
      "robot": 5,
      "teamNumber": 2526,
      "startPosition": 2,
      "isNoShow": false,
      "hasMoved": true,
      "autoSpeakerScoredCount": 4,
      "autoSpeakerMissedCount": 0,
      "autoGamePiecePath": 177,
      "autoFoulCount": 2,
      "ampScoredCount": 3,
      "speakerScoredCount": 5,
      "feederShotsCount": 0,
      "noteInTrapCount": 0,
      "teleopFoulCount": 1,
      "endPosition": 0,
      "offenseSkillRating": 3,
      "defenseSkillRating": 3,
      "hasDiedOrTippedOver": false,
      "yellowRedCard": 1,
      "comments": "Hi There! SOS - match (43)"
  },
  {
      "scouter": "SOS",
      "matchNumber": 44,
      "robot": 5,
      "teamNumber": 6160,
      "startPosition": 2,
      "isNoShow": false,
      "hasMoved": false,
      "autoSpeakerScoredCount": 1,
      "autoSpeakerMissedCount": 0,
      "autoGamePiecePath": 30,
      "autoFoulCount": 1,
      "ampScoredCount": 0,
      "speakerScoredCount": 6,
      "feederShotsCount": 0,
      "noteInTrapCount": 0,
      "teleopFoulCount": 0,
      "endPosition": 1,
      "offenseSkillRating": 1,
      "defenseSkillRating": 1,
      "hasDiedOrTippedOver": false,
      "yellowRedCard": 1,
      "comments": "Hi There! SOS - match (44)"
  },
  {
      "scouter": "SOS",
      "matchNumber": 45,
      "robot": 5,
      "teamNumber": 4778,
      "startPosition": 2,
      "isNoShow": false,
      "hasMoved": true,
      "autoSpeakerScoredCount": 4,
      "autoSpeakerMissedCount": 0,
      "autoGamePiecePath": 21,
      "autoFoulCount": 0,
      "ampScoredCount": 3,
      "speakerScoredCount": 6,
      "feederShotsCount": 0,
      "noteInTrapCount": 0,
      "teleopFoulCount": 0,
      "endPosition": 2,
      "offenseSkillRating": 2,
      "defenseSkillRating": 2,
      "hasDiedOrTippedOver": false,
      "yellowRedCard": 1,
      "comments": "Hi There! SOS - match (45)"
  },
  {
      "scouter": "SOS",
      "matchNumber": 46,
      "robot": 5,
      "teamNumber": 5253,
      "startPosition": 2,
      "isNoShow": false,
      "hasMoved": true,
      "autoSpeakerScoredCount": 2,
      "autoSpeakerMissedCount": 0,
      "autoGamePiecePath": 20,
      "autoFoulCount": 0,
      "ampScoredCount": 7,
      "speakerScoredCount": 7,
      "feederShotsCount": 0,
      "noteInTrapCount": 0,
      "teleopFoulCount": 0,
      "endPosition": 3,
      "offenseSkillRating": 1,
      "defenseSkillRating": 1,
      "hasDiedOrTippedOver": false,
      "yellowRedCard": 1,
      "comments": "Hi There! SOS - match (46)"
  },
  {
      "scouter": "SOS",
      "matchNumber": 47,
      "robot": 5,
      "teamNumber": 3197,
      "startPosition": 2,
      "isNoShow": false,
      "hasMoved": true,
      "autoSpeakerScoredCount": 1,
      "autoSpeakerMissedCount": 0,
      "autoGamePiecePath": 184,
      "autoFoulCount": 0,
      "ampScoredCount": 4,
      "speakerScoredCount": 8,
      "feederShotsCount": 0,
      "noteInTrapCount": 0,
      "teleopFoulCount": 0,
      "endPosition": 1,
      "offenseSkillRating": 0,
      "defenseSkillRating": 2,
      "hasDiedOrTippedOver": false,
      "yellowRedCard": 1,
      "comments": "Hi There! SOS - match (47)"
  },
  {
      "scouter": "SOS",
      "matchNumber": 48,
      "robot": 5,
      "teamNumber": 4741,
      "startPosition": 2,
      "isNoShow": false,
      "hasMoved": true,
      "autoSpeakerScoredCount": 3,
      "autoSpeakerMissedCount": 0,
      "autoGamePiecePath": 8,
      "autoFoulCount": 0,
      "ampScoredCount": 6,
      "speakerScoredCount": 4,
      "feederShotsCount": 0,
      "noteInTrapCount": 0,
      "teleopFoulCount": 1,
      "endPosition": 0,
      "offenseSkillRating": 2,
      "defenseSkillRating": 2,
      "hasDiedOrTippedOver": false,
      "yellowRedCard": 1,
      "comments": "Hi There! SOS - match (48)"
  },
  {
      "scouter": "SOS",
      "matchNumber": 49,
      "robot": 5,
      "teamNumber": 5690,
      "startPosition": 2,
      "isNoShow": false,
      "hasMoved": false,
      "autoSpeakerScoredCount": 4,
      "autoSpeakerMissedCount": 0,
      "autoGamePiecePath": 70,
      "autoFoulCount": 0,
      "ampScoredCount": 5,
      "speakerScoredCount": 15,
      "feederShotsCount": 0,
      "noteInTrapCount": 0,
      "teleopFoulCount": 0,
      "endPosition": 4,
      "offenseSkillRating": 0,
      "defenseSkillRating": 3,
      "hasDiedOrTippedOver": false,
      "yellowRedCard": 1,
      "comments": "Hi There! SOS - match (49)"
  },
  {
      "scouter": "SOS",
      "matchNumber": 50,
      "robot": 5,
      "teamNumber": 2847,
      "startPosition": 2,
      "isNoShow": false,
      "hasMoved": true,
      "autoSpeakerScoredCount": 3,
      "autoSpeakerMissedCount": 0,
      "autoGamePiecePath": 245,
      "autoFoulCount": 0,
      "ampScoredCount": 1,
      "speakerScoredCount": 11,
      "feederShotsCount": 0,
      "noteInTrapCount": 0,
      "teleopFoulCount": 0,
      "endPosition": 2,
      "offenseSkillRating": 0,
      "defenseSkillRating": 0,
      "hasDiedOrTippedOver": false,
      "yellowRedCard": 1,
      "comments": "Hi There! SOS - match (50)"
  },
  {
      "scouter": "SOS",
      "matchNumber": 51,
      "robot": 5,
      "teamNumber": 4174,
      "startPosition": 2,
      "isNoShow": false,
      "hasMoved": true,
      "autoSpeakerScoredCount": 3,
      "autoSpeakerMissedCount": 0,
      "autoGamePiecePath": 208,
      "autoFoulCount": 1,
      "ampScoredCount": 4,
      "speakerScoredCount": 9,
      "feederShotsCount": 0,
      "noteInTrapCount": 0,
      "teleopFoulCount": 0,
      "endPosition": 1,
      "offenseSkillRating": 2,
      "defenseSkillRating": 3,
      "hasDiedOrTippedOver": false,
      "yellowRedCard": 1,
      "comments": "Hi There! SOS - match (51)"
  },
  {
      "scouter": "SOS",
      "matchNumber": 52,
      "robot": 5,
      "teamNumber": 6381,
      "startPosition": 2,
      "isNoShow": false,
      "hasMoved": true,
      "autoSpeakerScoredCount": 1,
      "autoSpeakerMissedCount": 0,
      "autoGamePiecePath": 39,
      "autoFoulCount": 0,
      "ampScoredCount": 0,
      "speakerScoredCount": 10,
      "feederShotsCount": 0,
      "noteInTrapCount": 0,
      "teleopFoulCount": 0,
      "endPosition": 4,
      "offenseSkillRating": 3,
      "defenseSkillRating": 0,
      "hasDiedOrTippedOver": false,
      "yellowRedCard": 1,
      "comments": "Hi There! SOS - match (52)"
  },
  {
      "scouter": "SOS",
      "matchNumber": 53,
      "robot": 5,
      "teamNumber": 4656,
      "startPosition": 2,
      "isNoShow": false,
      "hasMoved": true,
      "autoSpeakerScoredCount": 5,
      "autoSpeakerMissedCount": 0,
      "autoGamePiecePath": 88,
      "autoFoulCount": 0,
      "ampScoredCount": 7,
      "speakerScoredCount": 3,
      "feederShotsCount": 0,
      "noteInTrapCount": 0,
      "teleopFoulCount": 0,
      "endPosition": 4,
      "offenseSkillRating": 0,
      "defenseSkillRating": 0,
      "hasDiedOrTippedOver": false,
      "yellowRedCard": 1,
      "comments": "Hi There! SOS - match (53)"
  },
  {
      "scouter": "SOS",
      "matchNumber": 54,
      "robot": 5,
      "teamNumber": 5903,
      "startPosition": 2,
      "isNoShow": false,
      "hasMoved": true,
      "autoSpeakerScoredCount": 1,
      "autoSpeakerMissedCount": 0,
      "autoGamePiecePath": 70,
      "autoFoulCount": 0,
      "ampScoredCount": 3,
      "speakerScoredCount": 13,
      "feederShotsCount": 0,
      "noteInTrapCount": 0,
      "teleopFoulCount": 0,
      "endPosition": 4,
      "offenseSkillRating": 3,
      "defenseSkillRating": 2,
      "hasDiedOrTippedOver": false,
      "yellowRedCard": 1,
      "comments": "Hi There! SOS - match (54)"
  },
  {
      "scouter": "SOS",
      "matchNumber": 55,
      "robot": 5,
      "teamNumber": 3267,
      "startPosition": 2,
      "isNoShow": false,
      "hasMoved": true,
      "autoSpeakerScoredCount": 2,
      "autoSpeakerMissedCount": 0,
      "autoGamePiecePath": 71,
      "autoFoulCount": 0,
      "ampScoredCount": 1,
      "speakerScoredCount": 8,
      "feederShotsCount": 0,
      "noteInTrapCount": 0,
      "teleopFoulCount": 0,
      "endPosition": 2,
      "offenseSkillRating": 2,
      "defenseSkillRating": 1,
      "hasDiedOrTippedOver": false,
      "yellowRedCard": 1,
      "comments": "Hi There! SOS - match (55)"
  },
  {
      "scouter": "SOS",
      "matchNumber": 56,
      "robot": 5,
      "teamNumber": 8422,
      "startPosition": 2,
      "isNoShow": false,
      "hasMoved": false,
      "autoSpeakerScoredCount": 5,
      "autoSpeakerMissedCount": 0,
      "autoGamePiecePath": 63,
      "autoFoulCount": 0,
      "ampScoredCount": 4,
      "speakerScoredCount": 6,
      "feederShotsCount": 0,
      "noteInTrapCount": 0,
      "teleopFoulCount": 0,
      "endPosition": 1,
      "offenseSkillRating": 1,
      "defenseSkillRating": 1,
      "hasDiedOrTippedOver": false,
      "yellowRedCard": 1,
      "comments": "Hi There! SOS - match (56)"
  },
  {
      "scouter": "SOS",
      "matchNumber": 57,
      "robot": 5,
      "teamNumber": 6421,
      "startPosition": 2,
      "isNoShow": false,
      "hasMoved": true,
      "autoSpeakerScoredCount": 3,
      "autoSpeakerMissedCount": 0,
      "autoGamePiecePath": 59,
      "autoFoulCount": 0,
      "ampScoredCount": 3,
      "speakerScoredCount": 0,
      "feederShotsCount": 0,
      "noteInTrapCount": 0,
      "teleopFoulCount": 0,
      "endPosition": 3,
      "offenseSkillRating": 1,
      "defenseSkillRating": 0,
      "hasDiedOrTippedOver": false,
      "yellowRedCard": 1,
      "comments": "Hi There! SOS - match (57)"
  },
  {
      "scouter": "SOS",
      "matchNumber": 58,
      "robot": 5,
      "teamNumber": 1732,
      "startPosition": 2,
      "isNoShow": false,
      "hasMoved": true,
      "autoSpeakerScoredCount": 4,
      "autoSpeakerMissedCount": 0,
      "autoGamePiecePath": 100,
      "autoFoulCount": 0,
      "ampScoredCount": 8,
      "speakerScoredCount": 11,
      "feederShotsCount": 0,
      "noteInTrapCount": 0,
      "teleopFoulCount": 0,
      "endPosition": 3,
      "offenseSkillRating": 2,
      "defenseSkillRating": 3,
      "hasDiedOrTippedOver": false,
      "yellowRedCard": 1,
      "comments": "Hi There! SOS - match (58)"
  },
  {
      "scouter": "SOS",
      "matchNumber": 59,
      "robot": 5,
      "teamNumber": 2847,
      "startPosition": 2,
      "isNoShow": false,
      "hasMoved": true,
      "autoSpeakerScoredCount": 2,
      "autoSpeakerMissedCount": 0,
      "autoGamePiecePath": 107,
      "autoFoulCount": 0,
      "ampScoredCount": 4,
      "speakerScoredCount": 10,
      "feederShotsCount": 0,
      "noteInTrapCount": 1,
      "teleopFoulCount": 0,
      "endPosition": 3,
      "offenseSkillRating": 0,
      "defenseSkillRating": 3,
      "hasDiedOrTippedOver": false,
      "yellowRedCard": 1,
      "comments": "Hi There! SOS - match (59)"
  },
  {
      "scouter": "SOS",
      "matchNumber": 60,
      "robot": 5,
      "teamNumber": 7915,
      "startPosition": 2,
      "isNoShow": false,
      "hasMoved": true,
      "autoSpeakerScoredCount": 3,
      "autoSpeakerMissedCount": 0,
      "autoGamePiecePath": 204,
      "autoFoulCount": 0,
      "ampScoredCount": 1,
      "speakerScoredCount": 14,
      "feederShotsCount": 0,
      "noteInTrapCount": 0,
      "teleopFoulCount": 2,
      "endPosition": 0,
      "offenseSkillRating": 1,
      "defenseSkillRating": 3,
      "hasDiedOrTippedOver": false,
      "yellowRedCard": 1,
      "comments": "Hi There! SOS - match (60)"
  },
  {
      "scouter": "SOS",
      "matchNumber": 61,
      "robot": 5,
      "teamNumber": 2526,
      "startPosition": 2,
      "isNoShow": false,
      "hasMoved": false,
      "autoSpeakerScoredCount": 3,
      "autoSpeakerMissedCount": 0,
      "autoGamePiecePath": 190,
      "autoFoulCount": 1,
      "ampScoredCount": 0,
      "speakerScoredCount": 6,
      "feederShotsCount": 0,
      "noteInTrapCount": 0,
      "teleopFoulCount": 2,
      "endPosition": 4,
      "offenseSkillRating": 1,
      "defenseSkillRating": 1,
      "hasDiedOrTippedOver": false,
      "yellowRedCard": 1,
      "comments": "Hi There! SOS - match (61)"
  },
  {
      "scouter": "SOS",
      "matchNumber": 62,
      "robot": 5,
      "teamNumber": 4656,
      "startPosition": 2,
      "isNoShow": false,
      "hasMoved": false,
      "autoSpeakerScoredCount": 2,
      "autoSpeakerMissedCount": 0,
      "autoGamePiecePath": 77,
      "autoFoulCount": 0,
      "ampScoredCount": 0,
      "speakerScoredCount": 7,
      "feederShotsCount": 0,
      "noteInTrapCount": 0,
      "teleopFoulCount": 0,
      "endPosition": 3,
      "offenseSkillRating": 0,
      "defenseSkillRating": 2,
      "hasDiedOrTippedOver": false,
      "yellowRedCard": 1,
      "comments": "Hi There! SOS - match (62)"
  },
  {
      "scouter": "SOS",
      "matchNumber": 63,
      "robot": 5,
      "teamNumber": 6217,
      "startPosition": 2,
      "isNoShow": false,
      "hasMoved": true,
      "autoSpeakerScoredCount": 1,
      "autoSpeakerMissedCount": 0,
      "autoGamePiecePath": 179,
      "autoFoulCount": 0,
      "ampScoredCount": 6,
      "speakerScoredCount": 1,
      "feederShotsCount": 0,
      "noteInTrapCount": 0,
      "teleopFoulCount": 0,
      "endPosition": 2,
      "offenseSkillRating": 2,
      "defenseSkillRating": 1,
      "hasDiedOrTippedOver": true,
      "yellowRedCard": 1,
      "comments": "Hi There! SOS - match (63)"
  },
  {
      "scouter": "SOS",
      "matchNumber": 64,
      "robot": 5,
      "teamNumber": 2181,
      "startPosition": 2,
      "isNoShow": false,
      "hasMoved": true,
      "autoSpeakerScoredCount": 2,
      "autoSpeakerMissedCount": 0,
      "autoGamePiecePath": 18,
      "autoFoulCount": 1,
      "ampScoredCount": 0,
      "speakerScoredCount": 6,
      "feederShotsCount": 0,
      "noteInTrapCount": 0,
      "teleopFoulCount": 2,
      "endPosition": 2,
      "offenseSkillRating": 2,
      "defenseSkillRating": 2,
      "hasDiedOrTippedOver": false,
      "yellowRedCard": 1,
      "comments": "Hi There! SOS - match (64)"
  },
  {
      "scouter": "SOS",
      "matchNumber": 65,
      "robot": 5,
      "teamNumber": 5690,
      "startPosition": 2,
      "isNoShow": false,
      "hasMoved": true,
      "autoSpeakerScoredCount": 3,
      "autoSpeakerMissedCount": 0,
      "autoGamePiecePath": 123,
      "autoFoulCount": 0,
      "ampScoredCount": 4,
      "speakerScoredCount": 7,
      "feederShotsCount": 0,
      "noteInTrapCount": 0,
      "teleopFoulCount": 0,
      "endPosition": 0,
      "offenseSkillRating": 1,
      "defenseSkillRating": 2,
      "hasDiedOrTippedOver": false,
      "yellowRedCard": 1,
      "comments": "Hi There! SOS - match (65)"
  },
  {
      "scouter": "SOS",
      "matchNumber": 66,
      "robot": 5,
      "teamNumber": 4624,
      "startPosition": 2,
      "isNoShow": false,
      "hasMoved": true,
      "autoSpeakerScoredCount": 1,
      "autoSpeakerMissedCount": 0,
      "autoGamePiecePath": 143,
      "autoFoulCount": 0,
      "ampScoredCount": 4,
      "speakerScoredCount": 6,
      "feederShotsCount": 0,
      "noteInTrapCount": 0,
      "teleopFoulCount": 0,
      "endPosition": 0,
      "offenseSkillRating": 3,
      "defenseSkillRating": 1,
      "hasDiedOrTippedOver": false,
      "yellowRedCard": 1,
      "comments": "Hi There! SOS - match (66)"
  },
  {
      "scouter": "SOS",
      "matchNumber": 67,
      "robot": 5,
      "teamNumber": 4181,
      "startPosition": 2,
      "isNoShow": false,
      "hasMoved": false,
      "autoSpeakerScoredCount": 2,
      "autoSpeakerMissedCount": 0,
      "autoGamePiecePath": 183,
      "autoFoulCount": 0,
      "ampScoredCount": 2,
      "speakerScoredCount": 5,
      "feederShotsCount": 0,
      "noteInTrapCount": 0,
      "teleopFoulCount": 0,
      "endPosition": 2,
      "offenseSkillRating": 1,
      "defenseSkillRating": 1,
      "hasDiedOrTippedOver": false,
      "yellowRedCard": 1,
      "comments": "Hi There! SOS - match (67)"
  },
  {
      "scouter": "SOS",
      "matchNumber": 68,
      "robot": 5,
      "teamNumber": 5348,
      "startPosition": 2,
      "isNoShow": false,
      "hasMoved": true,
      "autoSpeakerScoredCount": 3,
      "autoSpeakerMissedCount": 0,
      "autoGamePiecePath": 24,
      "autoFoulCount": 0,
      "ampScoredCount": 6,
      "speakerScoredCount": 5,
      "feederShotsCount": 0,
      "noteInTrapCount": 0,
      "teleopFoulCount": 4,
      "endPosition": 0,
      "offenseSkillRating": 1,
      "defenseSkillRating": 1,
      "hasDiedOrTippedOver": false,
      "yellowRedCard": 1,
      "comments": "Hi There! SOS - match (68)"
  },
  {
      "scouter": "SOS",
      "matchNumber": 69,
      "robot": 5,
      "teamNumber": 2823,
      "startPosition": 2,
      "isNoShow": false,
      "hasMoved": false,
      "autoSpeakerScoredCount": 4,
      "autoSpeakerMissedCount": 0,
      "autoGamePiecePath": 155,
      "autoFoulCount": 1,
      "ampScoredCount": 4,
      "speakerScoredCount": 7,
      "feederShotsCount": 0,
      "noteInTrapCount": 0,
      "teleopFoulCount": 0,
      "endPosition": 4,
      "offenseSkillRating": 3,
      "defenseSkillRating": 2,
      "hasDiedOrTippedOver": false,
      "yellowRedCard": 1,
      "comments": "Hi There! SOS - match (69)"
  },
  {
      "scouter": "SOS",
      "matchNumber": 70,
      "robot": 5,
      "teamNumber": 7038,
      "startPosition": 2,
      "isNoShow": false,
      "hasMoved": false,
      "autoSpeakerScoredCount": 4,
      "autoSpeakerMissedCount": 0,
      "autoGamePiecePath": 253,
      "autoFoulCount": 0,
      "ampScoredCount": 1,
      "speakerScoredCount": 7,
      "feederShotsCount": 0,
      "noteInTrapCount": 0,
      "teleopFoulCount": 4,
      "endPosition": 3,
      "offenseSkillRating": 2,
      "defenseSkillRating": 2,
      "hasDiedOrTippedOver": false,
      "yellowRedCard": 1,
      "comments": "Hi There! SOS - match (70)"
  },
  {
      "scouter": "SOS",
      "matchNumber": 71,
      "robot": 5,
      "teamNumber": 8422,
      "startPosition": 2,
      "isNoShow": false,
      "hasMoved": false,
      "autoSpeakerScoredCount": 4,
      "autoSpeakerMissedCount": 0,
      "autoGamePiecePath": 23,
      "autoFoulCount": 0,
      "ampScoredCount": 0,
      "speakerScoredCount": 11,
      "feederShotsCount": 0,
      "noteInTrapCount": 0,
      "teleopFoulCount": 0,
      "endPosition": 0,
      "offenseSkillRating": 1,
      "defenseSkillRating": 2,
      "hasDiedOrTippedOver": false,
      "yellowRedCard": 1,
      "comments": "Hi There! SOS - match (71)"
  },
  {
      "scouter": "SOS",
      "matchNumber": 72,
      "robot": 5,
      "teamNumber": 4011,
      "startPosition": 2,
      "isNoShow": false,
      "hasMoved": true,
      "autoSpeakerScoredCount": 2,
      "autoSpeakerMissedCount": 0,
      "autoGamePiecePath": 243,
      "autoFoulCount": 0,
      "ampScoredCount": 0,
      "speakerScoredCount": 9,
      "feederShotsCount": 0,
      "noteInTrapCount": 0,
      "teleopFoulCount": 0,
      "endPosition": 3,
      "offenseSkillRating": 0,
      "defenseSkillRating": 1,
      "hasDiedOrTippedOver": false,
      "yellowRedCard": 1,
      "comments": "Hi There! SOS - match (72)"
  },
  {
      "scouter": "SOS",
      "matchNumber": 73,
      "robot": 5,
      "teamNumber": 6217,
      "startPosition": 2,
      "isNoShow": false,
      "hasMoved": true,
      "autoSpeakerScoredCount": 2,
      "autoSpeakerMissedCount": 0,
      "autoGamePiecePath": 93,
      "autoFoulCount": 0,
      "ampScoredCount": 4,
      "speakerScoredCount": 4,
      "feederShotsCount": 0,
      "noteInTrapCount": 0,
      "teleopFoulCount": 2,
      "endPosition": 3,
      "offenseSkillRating": 1,
      "defenseSkillRating": 1,
      "hasDiedOrTippedOver": false,
      "yellowRedCard": 1,
      "comments": "Hi There! SOS - match (73)"
  },
  {
      "scouter": "SOS",
      "matchNumber": 74,
      "robot": 5,
      "teamNumber": 2052,
      "startPosition": 2,
      "isNoShow": false,
      "hasMoved": true,
      "autoSpeakerScoredCount": 5,
      "autoSpeakerMissedCount": 0,
      "autoGamePiecePath": 56,
      "autoFoulCount": 0,
      "ampScoredCount": 0,
      "speakerScoredCount": 6,
      "feederShotsCount": 0,
      "noteInTrapCount": 0,
      "teleopFoulCount": 1,
      "endPosition": 4,
      "offenseSkillRating": 1,
      "defenseSkillRating": 2,
      "hasDiedOrTippedOver": false,
      "yellowRedCard": 1,
      "comments": "Hi There! SOS - match (74)"
  },
  {
      "scouter": "SOS",
      "matchNumber": 75,
      "robot": 5,
      "teamNumber": 3055,
      "startPosition": 2,
      "isNoShow": false,
      "hasMoved": true,
      "autoSpeakerScoredCount": 2,
      "autoSpeakerMissedCount": 0,
      "autoGamePiecePath": 114,
      "autoFoulCount": 0,
      "ampScoredCount": 6,
      "speakerScoredCount": 3,
      "feederShotsCount": 0,
      "noteInTrapCount": 0,
      "teleopFoulCount": 2,
      "endPosition": 3,
      "offenseSkillRating": 3,
      "defenseSkillRating": 1,
      "hasDiedOrTippedOver": false,
      "yellowRedCard": 1,
      "comments": "Hi There! SOS - match (75)"
  },
  {
      "scouter": "SOS",
      "matchNumber": 76,
      "robot": 5,
      "teamNumber": 8298,
      "startPosition": 2,
      "isNoShow": false,
      "hasMoved": false,
      "autoSpeakerScoredCount": 2,
      "autoSpeakerMissedCount": 0,
      "autoGamePiecePath": 194,
      "autoFoulCount": 1,
      "ampScoredCount": 0,
      "speakerScoredCount": 6,
      "feederShotsCount": 0,
      "noteInTrapCount": 0,
      "teleopFoulCount": 0,
      "endPosition": 2,
      "offenseSkillRating": 2,
      "defenseSkillRating": 3,
      "hasDiedOrTippedOver": false,
      "yellowRedCard": 1,
      "comments": "Hi There! SOS - match (76)"
  },
  {
      "scouter": "SOS",
      "matchNumber": 77,
      "robot": 5,
      "teamNumber": 7068,
      "startPosition": 2,
      "isNoShow": false,
      "hasMoved": true,
      "autoSpeakerScoredCount": 3,
      "autoSpeakerMissedCount": 0,
      "autoGamePiecePath": 24,
      "autoFoulCount": 0,
      "ampScoredCount": 3,
      "speakerScoredCount": 11,
      "feederShotsCount": 0,
      "noteInTrapCount": 0,
      "teleopFoulCount": 0,
      "endPosition": 1,
      "offenseSkillRating": 0,
      "defenseSkillRating": 3,
      "hasDiedOrTippedOver": false,
      "yellowRedCard": 1,
      "comments": "Hi There! SOS - match (77)"
  },
  {
      "scouter": "SOS",
      "matchNumber": 78,
      "robot": 5,
      "teamNumber": 2181,
      "startPosition": 2,
      "isNoShow": false,
      "hasMoved": true,
      "autoSpeakerScoredCount": 3,
      "autoSpeakerMissedCount": 0,
      "autoGamePiecePath": 124,
      "autoFoulCount": 0,
      "ampScoredCount": 5,
      "speakerScoredCount": 10,
      "feederShotsCount": 0,
      "noteInTrapCount": 0,
      "teleopFoulCount": 0,
      "endPosition": 1,
      "offenseSkillRating": 1,
      "defenseSkillRating": 2,
      "hasDiedOrTippedOver": false,
      "yellowRedCard": 1,
      "comments": "Hi There! SOS - match (78)"
  },
  {
      "scouter": "SOS",
      "matchNumber": 79,
      "robot": 5,
      "teamNumber": 5253,
      "startPosition": 2,
      "isNoShow": false,
      "hasMoved": true,
      "autoSpeakerScoredCount": 5,
      "autoSpeakerMissedCount": 0,
      "autoGamePiecePath": 97,
      "autoFoulCount": 1,
      "ampScoredCount": 6,
      "speakerScoredCount": 10,
      "feederShotsCount": 0,
      "noteInTrapCount": 0,
      "teleopFoulCount": 0,
      "endPosition": 4,
      "offenseSkillRating": 3,
      "defenseSkillRating": 1,
      "hasDiedOrTippedOver": false,
      "yellowRedCard": 1,
      "comments": "Hi There! SOS - match (79)"
  },
  {
      "scouter": "SOS",
      "matchNumber": 80,
      "robot": 5,
      "teamNumber": 6160,
      "startPosition": 2,
      "isNoShow": false,
      "hasMoved": true,
      "autoSpeakerScoredCount": 0,
      "autoSpeakerMissedCount": 0,
      "autoGamePiecePath": 244,
      "autoFoulCount": 0,
      "ampScoredCount": 2,
      "speakerScoredCount": 10,
      "feederShotsCount": 0,
      "noteInTrapCount": 0,
      "teleopFoulCount": 0,
      "endPosition": 3,
      "offenseSkillRating": 2,
      "defenseSkillRating": 3,
      "hasDiedOrTippedOver": false,
      "yellowRedCard": 1,
      "comments": "Hi There! SOS - match (80)"
  },
  {
      "scouter": "SOS",
      "matchNumber": 81,
      "robot": 5,
      "teamNumber": 1816,
      "startPosition": 2,
      "isNoShow": false,
      "hasMoved": true,
      "autoSpeakerScoredCount": 1,
      "autoSpeakerMissedCount": 0,
      "autoGamePiecePath": 211,
      "autoFoulCount": 0,
      "ampScoredCount": 5,
      "speakerScoredCount": 8,
      "feederShotsCount": 0,
      "noteInTrapCount": 0,
      "teleopFoulCount": 0,
      "endPosition": 3,
      "offenseSkillRating": 0,
      "defenseSkillRating": 2,
      "hasDiedOrTippedOver": true,
      "yellowRedCard": 1,
      "comments": "Hi There! SOS - match (81)"
  },
  {
      "scouter": "SOS",
      "matchNumber": 82,
      "robot": 5,
      "teamNumber": 2503,
      "startPosition": 2,
      "isNoShow": false,
      "hasMoved": true,
      "autoSpeakerScoredCount": 3,
      "autoSpeakerMissedCount": 0,
      "autoGamePiecePath": 146,
      "autoFoulCount": 0,
      "ampScoredCount": 7,
      "speakerScoredCount": 4,
      "feederShotsCount": 0,
      "noteInTrapCount": 0,
      "teleopFoulCount": 0,
      "endPosition": 3,
      "offenseSkillRating": 0,
      "defenseSkillRating": 3,
      "hasDiedOrTippedOver": false,
      "yellowRedCard": 1,
      "comments": "Hi There! SOS - match (82)"
  },
  {
      "scouter": "SOS",
      "matchNumber": 83,
      "robot": 5,
      "teamNumber": 3291,
      "startPosition": 2,
      "isNoShow": false,
      "hasMoved": true,
      "autoSpeakerScoredCount": 2,
      "autoSpeakerMissedCount": 0,
      "autoGamePiecePath": 26,
      "autoFoulCount": 0,
      "ampScoredCount": 0,
      "speakerScoredCount": 15,
      "feederShotsCount": 0,
      "noteInTrapCount": 0,
      "teleopFoulCount": 0,
      "endPosition": 1,
      "offenseSkillRating": 3,
      "defenseSkillRating": 0,
      "hasDiedOrTippedOver": false,
      "yellowRedCard": 1,
      "comments": "Hi There! SOS - match (83)"
  }
]