[{"scouter":"LH","matchNumber":1,"robot":"0","teamNumber":"3082","startPosition":2,"isNoShow":false,"hasMovedOutOfStartingZone":true,"autoNetScoredCount":0,"autoNetMissedCount":0,"autoHoopScoredCount":0,"autoHoopMissedCount":0,"autoPenaltyCount":0,"netScoredCount":0,"netMissedCount":4,"hoopScoredCount":0,"hoopMissedCount":0,"teleopPenaltyCount":0,"sharkSaver":true,"endInStartingZone":true,"offenseSkillRating":1,"defenseSkillRating":0,"hasDiedOrTippedOver":false,"yellowRedCard":0,"comments":"Uneffective scoring","autoPointsScoredCount":5,"autoPointsMissedCount":0,"pointsScoredCount":0,"pointsMissedCount":8,"totalPointsScoredCount":10,"totalPointsMissedCount":8,"totalPenaltyCount":0},{"scouter":"LH","matchNumber":2,"robot":"0","teamNumber":"2052A","startPosition":2,"isNoShow":false,"hasMovedOutOfStartingZone":true,"autoNetScoredCount":1,"autoNetMissedCount":0,"autoHoopScoredCount":0,"autoHoopMissedCount":0,"autoPenaltyCount":0,"netScoredCount":3,"netMissedCount":0,"hoopScoredCount":0,"hoopMissedCount":0,"teleopPenaltyCount":0,"sharkSaver":false,"endInStartingZone":true,"offenseSkillRating":3,"defenseSkillRating":0,"hasDiedOrTippedOver":false,"yellowRedCard":0,"comments":"Had a chance of the ball slipping out ","autoPointsScoredCount":9,"autoPointsMissedCount":0,"pointsScoredCount":6,"pointsMissedCount":0,"totalPointsScoredCount":20,"totalPointsMissedCount":0,"totalPenaltyCount":0},{"scouter":"LH","matchNumber":3,"robot":"0","teamNumber":"3206B","startPosition":2,"isNoShow":false,"hasMovedOutOfStartingZone":true,"autoNetScoredCount":0,"autoNetMissedCount":0,"autoHoopScoredCount":0,"autoHoopMissedCount":0,"autoPenaltyCount":0,"netScoredCount":1,"netMissedCount":0,"hoopScoredCount":0,"hoopMissedCount":0,"teleopPenaltyCount":0,"sharkSaver":false,"endInStartingZone":false,"offenseSkillRating":2,"defenseSkillRating":0,"hasDiedOrTippedOver":false,"yellowRedCard":0,"comments":"Reloading is ineffective ","autoPointsScoredCount":5,"autoPointsMissedCount":0,"pointsScoredCount":2,"pointsMissedCount":0,"totalPointsScoredCount":7,"totalPointsMissedCount":5,"totalPenaltyCount":0},{"scouter":"LH","matchNumber":4,"robot":"0","teamNumber":"2181B","startPosition":2,"isNoShow":false,"hasMovedOutOfStartingZone":true,"autoNetScoredCount":0,"autoNetMissedCount":0,"autoHoopScoredCount":0,"autoHoopMissedCount":0,"autoPenaltyCount":0,"netScoredCount":1,"netMissedCount":0,"hoopScoredCount":0,"hoopMissedCount":0,"teleopPenaltyCount":0,"sharkSaver":false,"endInStartingZone":false,"offenseSkillRating":0,"defenseSkillRating":0,"hasDiedOrTippedOver":true,"yellowRedCard":0,"comments":"Died","autoPointsScoredCount":5,"autoPointsMissedCount":0,"pointsScoredCount":2,"pointsMissedCount":0,"totalPointsScoredCount":7,"totalPointsMissedCount":5,"totalPenaltyCount":0},{"scouter":"LH","matchNumber":5,"robot":"0","teamNumber":"7850","startPosition":2,"isNoShow":false,"hasMovedOutOfStartingZone":false,"autoNetScoredCount":0,"autoNetMissedCount":0,"autoHoopScoredCount":0,"autoHoopMissedCount":0,"autoPenaltyCount":0,"netScoredCount":0,"netMissedCount":0,"hoopScoredCount":0,"hoopMissedCount":0,"teleopPenaltyCount":0,"sharkSaver":false,"endInStartingZone":true,"offenseSkillRating":1,"defenseSkillRating":1,"hasDiedOrTippedOver":false,"yellowRedCard":0,"comments":"Did not do anything except move a little","autoPointsScoredCount":0,"autoPointsMissedCount":5,"pointsScoredCount":0,"pointsMissedCount":0,"totalPointsScoredCount":5,"totalPointsMissedCount":5,"totalPenaltyCount":0},{"scouter":"LH","matchNumber":6,"robot":"0","teamNumber":"3206B","startPosition":2,"isNoShow":false,"hasMovedOutOfStartingZone":true,"autoNetScoredCount":0,"autoNetMissedCount":0,"autoHoopScoredCount":0,"autoHoopMissedCount":0,"autoPenaltyCount":0,"netScoredCount":1,"netMissedCount":0,"hoopScoredCount":0,"hoopMissedCount":0,"teleopPenaltyCount":0,"sharkSaver":false,"endInStartingZone":true,"offenseSkillRating":1,"defenseSkillRating":0,"hasDiedOrTippedOver":false,"yellowRedCard":0,"comments":"They picked up one ball","autoPointsScoredCount":5,"autoPointsMissedCount":0,"pointsScoredCount":2,"pointsMissedCount":0,"totalPointsScoredCount":12,"totalPointsMissedCount":0,"totalPenaltyCount":0},{"scouter":"LH","matchNumber":7,"robot":"0","teamNumber":"3206A","startPosition":2,"isNoShow":false,"hasMovedOutOfStartingZone":true,"autoNetScoredCount":1,"autoNetMissedCount":0,"autoHoopScoredCount":0,"autoHoopMissedCount":0,"autoPenaltyCount":0,"netScoredCount":4,"netMissedCount":1,"hoopScoredCount":0,"hoopMissedCount":0,"teleopPenaltyCount":0,"sharkSaver":false,"endInStartingZone":false,"offenseSkillRating":2,"defenseSkillRating":0,"hasDiedOrTippedOver":false,"yellowRedCard":0,"autoPointsScoredCount":9,"autoPointsMissedCount":0,"pointsScoredCount":8,"pointsMissedCount":2,"totalPointsScoredCount":17,"totalPointsMissedCount":7,"totalPenaltyCount":0}]